{
  "meta": {
    "title": "Learning Paths",
    "description": "Suggested sequences through the DTC teaching collection. Follow a track or jump to any guide."
  },
  "paths": [
    {
      "id": "post-trade",
      "title": "Post-Trade & DTC Core",
      "blurb": "How U.S. securities sit at DTC, become eligible, and settle in book-entry form.",
      "duration": "≈ 2–3 hours",
      "level": "Core",
      "color": "accent",
      "steps": [
        {
          "label": "Ownership & infrastructure — No Access",
          "href": "#",
          "module": "securities"
        },
        {
          "label": "Eligibility questionnaire (OA) — No Access",
          "href": "#",
          "module": "eligibility"
        },
        {
          "label": "Certificated deposit lifecycle — No Access",
          "href": "#",
          "module": "securities"
        }
      ]
    },
    {
      "id": "collateral",
      "title": "Collateral & UCC Article 8",
      "blurb": "Pledging book-entry securities: security entitlements, ACAs, and perfection.",
      "duration": "≈ 1–1.5 hours",
      "level": "Advanced",
      "color": "gold",
      "steps": [
        {
          "label": "Street name & Cede & Co. — No Access",
          "href": "#",
          "module": "securities"
        },
        {
          "label": "UCC Article 8 collateral — No Access",
          "href": "#",
          "module": "collateral"
        }
      ]
    },
    {
      "id": "govcon",
      "title": "Govcon Surety (SF 28)",
      "blurb": "Federal individual surety affidavits under FAR 28.203 and asset representation.",
      "duration": "≈ 45–60 min",
      "level": "Specialized",
      "color": "green",
      "steps": [
        {
          "label": "SF 28 teaching guide — No Access",
          "href": "#",
          "module": "sf28"
        }
      ]
    },
    {
      "id": "entities",
      "title": "Entity Structures",
      "blurb": "How LLCs, corporations, trusts, and foundations hold and title securities.",
      "duration": "≈ 2 hours",
      "level": "Supporting",
      "color": "accent",
      "steps": [
        {
          "label": "Corporate structures — No Access",
          "href": "#",
          "module": "corporate-structures"
        },
        {
          "label": "Trusts & fiduciary — No Access",
          "href": "#",
          "module": "trusts-fiduciary"
        },
        {
          "label": "Non-profit foundations — No Access",
          "href": "#",
          "module": "non-profit-foundations"
        }
      ]
    },
    {
      "id": "trade-finance",
      "title": "Trade Finance",
      "blurb": "Documentary collections and the Treasury International Bill of Exchange.",
      "duration": "≈ 45–60 min",
      "level": "Specialized",
      "color": "gold",
      "steps": [
        {
          "label": "Bill of exchange guide — No Access",
          "href": "#",
          "module": "trade"
        }
      ]
    }
  ]
}
